.bumpversion.cfg
.cookiecutterrc
.coveragerc
.editorconfig
AUTHORS.rst
CHANGELOG.rst
CONTRIBUTING.rst
LICENSE
MANIFEST.in
README.md
README.rst
setup.cfg
setup.py
tox.ini
ci/bootstrap.py
docs/authors.rst
docs/changelog.rst
docs/conf.py
docs/contributing.rst
docs/index.rst
docs/installation.rst
docs/readme.rst
docs/requirements.txt
docs/spelling_wordlist.txt
docs/usage.rst
docs/reference/cleanlog.rst
docs/reference/index.rst
src/cleanlog/__init__.py
src/cleanlog/__main__.py
src/cleanlog/cli.py
src/cleanlog/formatter.py
src/cleanlog/handler.py
src/cleanlog.egg-info/PKG-INFO
src/cleanlog.egg-info/SOURCES.txt
src/cleanlog.egg-info/dependency_links.txt
src/cleanlog.egg-info/entry_points.txt
src/cleanlog.egg-info/not-zip-safe
src/cleanlog.egg-info/requires.txt
src/cleanlog.egg-info/top_level.txt
tests/test_basiclogger.py
tests/test_cleanlog.py
tests/test_coloredlogger.py
tests/test_formatter.py
tests/test_getlogger.py